[
  {
    "symbol": "GOOGL",
    "name": "Alphabet Inc.",
    "price": 301.1300048828125,
    "change": -1.7584445791621643,
    "score": 85,
    "signals": {
      "en": [
        "\ud83d\udcc8 Uptrend",
        "\ud83d\udfe2 Oversold"
      ],
      "he": [
        "\ud83d\udcc8 \u05de\u05d2\u05de\u05ea \u05e2\u05dc\u05d9\u05d9\u05d4",
        "\ud83d\udfe2 \u05de\u05db\u05d9\u05e8\u05ea \u05d9\u05ea\u05e8"
      ]
    },
    "rsi": 34.717128377539964,
    "updated": "2026-03-03 16:28"
  },
  {
    "symbol": "TSLA",
    "name": "Tesla, Inc.",
    "price": 392.8399963378906,
    "change": -2.5984356828357162,
    "score": 85,
    "signals": {
      "en": [
        "\ud83d\udcc8 Uptrend",
        "\ud83d\udfe2 Oversold"
      ],
      "he": [
        "\ud83d\udcc8 \u05de\u05d2\u05de\u05ea \u05e2\u05dc\u05d9\u05d9\u05d4",
        "\ud83d\udfe2 \u05de\u05db\u05d9\u05e8\u05ea \u05d9\u05ea\u05e8"
      ]
    },
    "rsi": 29.34796660571324,
    "updated": "2026-03-03 16:28"
  },
  {
    "symbol": "NVDA",
    "name": "NVIDIA Corporation",
    "price": 179.47999572753906,
    "change": -1.6440158210433657,
    "score": 70,
    "signals": {
      "en": [
        "\ud83d\udcc8 Uptrend"
      ],
      "he": [
        "\ud83d\udcc8 \u05de\u05d2\u05de\u05ea \u05e2\u05dc\u05d9\u05d9\u05d4"
      ]
    },
    "rsi": 40.625003935556386,
    "updated": "2026-03-03 16:28"
  },
  {
    "symbol": "AAPL",
    "name": "Apple Inc.",
    "price": 262.20001220703125,
    "change": -0.9519450748154471,
    "score": 70,
    "signals": {
      "en": [
        "\ud83d\udcc8 Uptrend"
      ],
      "he": [
        "\ud83d\udcc8 \u05de\u05d2\u05de\u05ea \u05e2\u05dc\u05d9\u05d9\u05d4"
      ]
    },
    "rsi": 40.53432870037996,
    "updated": "2026-03-03 16:28"
  },
  {
    "symbol": "LLY",
    "name": "Eli Lilly and Company",
    "price": 1003.4000244140625,
    "change": -1.4312746651061672,
    "score": 70,
    "signals": {
      "en": [
        "\ud83d\udcc8 Uptrend"
      ],
      "he": [
        "\ud83d\udcc8 \u05de\u05d2\u05de\u05ea \u05e2\u05dc\u05d9\u05d9\u05d4"
      ]
    },
    "rsi": 45.78905696166312,
    "updated": "2026-03-03 16:28"
  },
  {
    "symbol": "BRK-B",
    "name": "Berkshire Hathaway Inc.",
    "price": 479.1300048828125,
    "change": -0.21659173122821349,
    "score": 45,
    "signals": {
      "en": [
        "\ud83d\udcc9 Downtrend",
        "\ud83d\udfe2 Oversold"
      ],
      "he": [
        "\ud83d\udcc9 \u05de\u05d2\u05de\u05ea \u05d9\u05e8\u05d9\u05d3\u05d4",
        "\ud83d\udfe2 \u05de\u05db\u05d9\u05e8\u05ea \u05d9\u05ea\u05e8"
      ]
    },
    "rsi": 31.803382574116668,
    "updated": "2026-03-03 16:28"
  },
  {
    "symbol": "AVGO",
    "name": "Broadcom Inc.",
    "price": 312.2200012207031,
    "change": -2.0701354845663302,
    "score": 45,
    "signals": {
      "en": [
        "\ud83d\udcc9 Downtrend",
        "\ud83d\udfe2 Oversold"
      ],
      "he": [
        "\ud83d\udcc9 \u05de\u05d2\u05de\u05ea \u05d9\u05e8\u05d9\u05d3\u05d4",
        "\ud83d\udfe2 \u05de\u05db\u05d9\u05e8\u05ea \u05d9\u05ea\u05e8"
      ]
    },
    "rsi": 28.0012408710855,
    "updated": "2026-03-03 16:28"
  },
  {
    "symbol": "MSFT",
    "name": "Microsoft Corporation",
    "price": 399.7799987792969,
    "change": 0.30862150897043006,
    "score": 30,
    "signals": {
      "en": [
        "\ud83d\udcc9 Downtrend"
      ],
      "he": [
        "\ud83d\udcc9 \u05de\u05d2\u05de\u05ea \u05d9\u05e8\u05d9\u05d3\u05d4"
      ]
    },
    "rsi": 40.57842638170961,
    "updated": "2026-03-03 16:28"
  },
  {
    "symbol": "AMZN",
    "name": "Amazon.com, Inc.",
    "price": 205.79420471191406,
    "change": -1.2456426341653508,
    "score": 30,
    "signals": {
      "en": [
        "\ud83d\udcc9 Downtrend"
      ],
      "he": [
        "\ud83d\udcc9 \u05de\u05d2\u05de\u05ea \u05d9\u05e8\u05d9\u05d3\u05d4"
      ]
    },
    "rsi": 48.494021958124875,
    "updated": "2026-03-03 16:28"
  },
  {
    "symbol": "META",
    "name": "Meta Platforms, Inc.",
    "price": 652.47998046875,
    "change": -0.16525140673820432,
    "score": 30,
    "signals": {
      "en": [
        "\ud83d\udcc9 Downtrend"
      ],
      "he": [
        "\ud83d\udcc9 \u05de\u05d2\u05de\u05ea \u05d9\u05e8\u05d9\u05d3\u05d4"
      ]
    },
    "rsi": 40.993487810207014,
    "updated": "2026-03-03 16:28"
  }
]